dexterCLI/__init__.py
dexterCLI/__main__.py
dexterCLI/api.py
dexterCLI/cli.py
dexterCLI/commands.py
dexterCLI-0.0.3.dist-info/LICENSE
dexterCLI-0.0.3.dist-info/METADATA
dexterCLI-0.0.3.dist-info/WHEEL
dexterCLI-0.0.3.dist-info/entry_points.txt
dexterCLI-0.0.3.dist-info/top_level.txt
dexterCLI-0.0.3.dist-info/RECORD
