Metadata-Version: 2.1
Name: dexterCLI
Version: 0.0.3
Summary: A command-line interface to the Dexter API
Author-email: Jon Ribbens <jribbens@unceasing.dev>
License: Copyright (c) 2022 Unceasing Digital Ltd
Project-URL: Bug Tracker, https://github.com/unceasing-dev/dexterCLI/issues
Project-URL: Homepage, https://github.com/unceasing-dev/dexterCLI#README
Classifier: Programming Language :: Python :: 3
Classifier: License :: OSI Approved :: MIT License
Classifier: Operating System :: OS Independent
Requires-Python: >=3.7
License-File: LICENSE
Requires-Dist: brotli >=1.0.9
Requires-Dist: requests >=2
